_version.py
invoker_cli.py
invoker_cli-1.0.0a35.dist-info/licenses/LICENSE
invoker_cli-1.0.0a35.dist-info/METADATA
invoker_cli-1.0.0a35.dist-info/WHEEL
invoker_cli-1.0.0a35.dist-info/entry_points.txt
invoker_cli-1.0.0a35.dist-info/top_level.txt
invoker_cli-1.0.0a35.dist-info/RECORD
