Metadata-Version: 2.4
Name: Invoker-CLI
Version: 1.0.0a35
Summary: Invoker-CLI is a command-line tool that provides a secure, encrypted keyring for managing and executing your Python scripts.
Author-email: Mohsen Ghorbani <m.ghorbani2357@gmail.com>
Maintainer-email: Mohsen Ghorbani <m.ghorbani2357@gmail.com>
License-Expression: GPL-3.0-or-later
Project-URL: Homepage, https://github.com/mghorbani2357/invoker-cli
Project-URL: Source, https://github.com/mghorbani2357/invoker-cli
Project-URL: Issues, https://github.com/mghorbani2357/invoker-cli/issues
Project-URL: Repository, https://github.com/mghorbani2357/invoker-cli.git
Keywords: invoker,cli,invoker-cli,packaging,git,setuptools
Classifier: Intended Audience :: Developers
Classifier: Operating System :: MacOS
Classifier: Operating System :: POSIX :: Linux
Classifier: Operating System :: OS Independent
Classifier: Topic :: Software Development :: Libraries :: Python Modules
Classifier: Programming Language :: Python :: 3.11
Classifier: Programming Language :: Python :: 3.12
Classifier: Programming Language :: Python :: 3.13
Classifier: Programming Language :: Python :: 3.14
Classifier: Programming Language :: Python :: Implementation :: PyPy
Requires-Python: >=3.11
License-File: LICENSE
Requires-Dist: cryptography
Requires-Dist: argon2-cffi
Dynamic: license-file
